{
  "vocabulary": [
    "λέγω",
    "ἔχω",
    "βλέπω",
    "ἐν",
    "ἐκ",
    "πρός",
    "ἀπό",
    "καί",
    "ἀλλά",
    "πέμπω",
    "διδάσκω",
    "σοφός",
    "εἰς",
    "οἰκία",
    "παιδίον",
    "βιβλίον",
    "πόλεμος",
    "εἰρήνη",
    "νῆσος",
    "λύω",
    "ἀγαθός",
    "κακός",
    "καλός",
    "μικρός",
    "μέγας",
    "δίκαιος",
    "ἄξιος",
    "ὁ",
    "ἄνθρωπος",
    "ἵππος",
    "λόγος",
    "δῶρον",
    "θεός",
    "στρατιώτης",
    "ψυχή",
    "θάλαττα",
    "ἀλήθεια",
    "γράφω",
    "παιδεύω",
    "φέρω",
    "ἄγω",
    "ἔρχομαι",
    "γίγνομαι",
    "βούλομαι",
    "δέχομαι"
  ],
  "flashcard_progress": {
    "ὁ": {
      "box": 1,
      "next_review": "2026-02-10"
    },
    "ἄνθρωπος": {
      "box": 3,
      "next_review": "2026-02-14"
    },
    "ἵππος": {
      "box": 2,
      "next_review": "2026-02-12"
    },
    "λόγος": {
      "box": 1,
      "next_review": "2026-02-10"
    },
    "δῶρον": {
      "box": 1,
      "next_review": "2026-02-10"
    },
    "θεός": {
      "box": 1,
      "next_review": "2026-02-10"
    },
    "στρατιώτης": {
      "box": 3,
      "next_review": "2026-02-14"
    },
    "ψυχή": {
      "box": 3,
      "next_review": "2026-02-14"
    },
    "θάλαττα": {
      "box": 3,
      "next_review": "2026-02-14"
    },
    "ἀλήθεια": {
      "box": 3,
      "next_review": "2026-02-14"
    },
    "οἰκία": {
      "box": 1,
      "next_review": "2026-02-10"
    },
    "παιδίον": {
      "box": 1,
      "next_review": "2026-02-10"
    },
    "βιβλίον": {
      "box": 1,
      "next_review": "2026-02-10"
    },
    "πόλεμος": {
      "box": 1,
      "next_review": "2026-02-10"
    },
    "εἰρήνη": {
      "box": 3,
      "next_review": "2026-02-14"
    },
    "νῆσος": {
      "box": 3,
      "next_review": "2026-02-14"
    },
    "λύω": {
      "box": 5,
      "next_review": "2026-03-12"
    },
    "γράφω": {
      "box": 2,
      "next_review": "2026-02-12"
    },
    "παιδεύω": {
      "box": 1,
      "next_review": "2026-02-10"
    },
    "πέμπω": {
      "box": 4,
      "next_review": "2026-02-24"
    },
    "φέρω": {
      "box": 2,
      "next_review": "2026-02-12"
    },
    "ἄγω": {
      "box": 1,
      "next_review": "2026-02-10"
    },
    "λέγω": {
      "box": 2,
      "next_review": "2026-02-13"
    },
    "ἔχω": {
      "box": 2,
      "next_review": "2026-02-12"
    },
    "βλέπω": {
      "box": 4,
      "next_review": "2026-02-22"
    },
    "διδάσκω": {
      "box": 2,
      "next_review": "2026-02-10"
    },
    "ἀγαθός": {
      "box": 3,
      "next_review": "2026-02-14"
    },
    "κακός": {
      "box": 1,
      "next_review": "2026-02-10"
    },
    "καλός": {
      "box": 1,
      "next_review": "2026-02-10"
    },
    "σοφός": {
      "box": 2,
      "next_review": "2026-02-10"
    },
    "μικρός": {
      "box": 1,
      "next_review": "2026-02-10"
    },
    "μέγας": {
      "box": 1,
      "next_review": "2026-02-10"
    },
    "δίκαιος": {
      "box": 2,
      "next_review": "2026-02-11"
    },
    "ἄξιος": {
      "box": 1,
      "next_review": "2026-02-10"
    },
    "ἐν": {
      "box": 4,
      "next_review": "2026-02-22"
    },
    "εἰς": {
      "box": 2,
      "next_review": "2026-02-11"
    },
    "ἐκ": {
      "box": 5,
      "next_review": "2026-03-10"
    },
    "πρός": {
      "box": 4,
      "next_review": "2026-02-22"
    },
    "ἀπό": {
      "box": 4,
      "next_review": "2026-02-22"
    },
    "καί": {
      "box": 4,
      "next_review": "2026-02-22"
    },
    "ἀλλά": {
      "box": 4,
      "next_review": "2026-02-22"
    },
    "ἔρχομαι": {
      "box": 1,
      "next_review": "2026-02-10"
    },
    "γίγνομαι": {
      "box": 1,
      "next_review": "2026-02-10"
    },
    "βούλομαι": {
      "box": 2,
      "next_review": "2026-02-12"
    },
    "δέχομαι": {
      "box": 1,
      "next_review": "2026-02-10"
    }
  },
  "sentences_completed": 69
}